{"amenity":{"fire_station":1010,"grave_yard":2094,"school":3229,"parking":11281,"police":535,"hospital":183,"fuel":791,"place_of_worship":2615,"bench":971,"toilets":301,"library":225,"post_office":235,"bar":221,"community_centre":65,"cafe":214,"bank":577,"social_facility":85,"shelter":592,"restaurant":1417,"prison":63,"loading_dock":96,"theatre":95,"waste_basket":475,"post_box":80,"college":52,"car_wash":159,"cinema":42,"atm":91,"fast_food":1100,"vending_machine":34,"doctors":83,"townhall":100,"marketplace":17,"sanitary_dump_station":6,"pharmacy":149,"courthouse":68,"dentist":48,"recycling":97,"public_building":91,"storage":20,"veterinary":82,"pub":56,"clinic":61,"pitch":2,"arts_centre":47,"drinking_water":153,"boat_rental":1,"charging_station":60,"public_building;police":1,"bbq":24,"bicycle_parking":596,"fountain":209,"nightclub":41,"stripclub":4,"funeral_home":1,"social_centre":4,"childcare":17,"kindergarten":32,"concession_stand":11,"first_aid":2,"university":84,"festival_grounds":1,"welfare":20,"bicycle_repair_station":21,"boat_storage":60,"trailer_park":9,"rest_area":1,"nursing_home":19,"waste_disposal":63,"gun_range":1,"care_provider_for disabled":1,"coworking_space":2,"scout_house":1,"accountants":1,"clock":6,"waste_transfer_station":3,"church":1,"parking_space":1101,"gym":4,"yes":1,"animal_shelter":8,"events_venue":3,"casino":7,"bicycle_rental":30,"self_storage":5,"body shop":1,"ski_school":1,"ski_rental":1,"compressed_air":3,"ice_cream":13,"Add Feature Undo / Redo Save Bing© 2019 Microsoft Corporation, © 2019 DigitalGlobe, ©CNES (2019) Distribution Airbus DS      2.15.4     Edits by csoulmaxericksonwegavision and 2 othersfast_food":1,"prison;school":1,"parking_entrance":34,"studio":10,"charity":43,"animal_boarding":4,"car_rental":13,"conference_center":1,"Distribution Center":1,"personal_care_attendant":1,"bureau_de_change":1,"bus_station":5,"retirement_home":2,"telephone":2,"smoking_area":1,"spa":1,"Shelter Slab":1,"antiques":1,"school;kindergarten":1,"stripbar":1,"ranger_station":1,"weighbridge":1,"arts_centre;cafe":1,"taxi":2,"exhibition_centre":1,"payment_centre":1,"crematorium":2,"pub;parking":1,"food_court":5,"farm_equipment":1,"greenhouse":1,"airpump":1,"apartment":1,"air_pump":1,"shower":1,"public_bath":1,"research_institute":3,"biergarten":1,"parking;post_office":1,"tax_preparer":1,"health_food_store":1,"internet_cafe":1,"condominiums":1,"security_booth":1,"reception_desk":2,"coffee_shop":1,"convention_centre":2,"public_bookcase":1,"embassy":1,"newsbox":2,"dojo":1},"shop":{"hardware":51,"convenience":369,"car_repair":370,"supermarket":330,"weapons":6,"antiques":53,"laundry":33,"car_parts":77,"second_hand":22,"tyres":10,"furniture":50,"beauty":77,"jewelry":44,"variety_store":105,"alcohol":134,"clothes":176,"pet":35,"farm":11,"hairdresser":138,"gift":56,"appliance":3,"leather":1,"funeral_directors":63,"hvac":2,"general":3,"car":134,"seed":1,"books":32,"boutique":9,"bakery":42,"doityourself":94,"computer":14,"electronics":37,"lawn_mower":2,"medical_supply":7,"office_supply":2,"optician":28,"florist":24,"charity":18,"department_store":69,"fabric":18,"farm_implement":8,"flooring":1,"glaziery":1,"pest_control":1,"tobacco":15,"mobile_phone":69,"yes":579,"musical_instrument":12,"paint":9,"electronics;furniture":1,"country_store":20,"heavy_machinery":1,"gun":1,"estate_agent":2,"glass":2,"storage_rental":69,"cosmetics":5,"outdoor":10,"roofing":1,"handmade":1,"confectionery":4,"chemist":16,"bicycle":27,"tailor":3,"building":13,"boat":1,"western":1,"shoes":31,"hobby":3,"eyewear":1,"video_games":10,"lawn":8,"mall":25,"coffee":6,"garden_centre":10,"salvage":32,"deli":11,"nutrition":1,"dairy":1,"firearms":1,"salon":3,"trailer":6,"craft":22,"stationery":23,"sports":28,"pyrotechnics":1,"butcher":7,"erotic":5,"toys":12,"hearing_aids":1,"pastry":2,"pet_grooming":2,"music":8,"trade":4,"art":8,"money_lender":7,"hifi":2,"bed":18,"pawnbroker":9,"greengrocer":10,"Smoky Valley Nursery":1,"games":2,"travel_agency":3,"motorcycle":8,"printing":2,"Yard_waste_and_mulch":1,"nutrition_supplements":7,"agrarian":1,"party":7,"interior_decoration":17,"frame":8,"guns":1,"wholesale":12,"fashion":2,"manicure":1,"community":13,"collector":1,"car_service":12,"pottery":1,"boat_repair":1,"dry_cleaning":17,"fireworks":1,"houseware":15,"vacuum_cleaner":2,"copyshop":6,"ice_cream":1,"video":9,"athletic_store":1,"kiosk":5,"tattoo":11,"science":1,"Soda":1,"check_cashing":1,"cable_tv":1,"dry_cleaning;laundry":1,"massage":7,"financial_services":2,"e-cigarette":6,"donuts":1,"medical":2,"beauty_supply":1,"pool":1,"beauty_products":1,"rental":2,"carpet":8,"supplement":1,"hairdresser_supply":1,"sign":1,"wood":1,"kitchen":4,"truck":7,"tractor":2,"trophy,engraving":1,"baby_goods":2,"regional":2,"atv":3,"groundskeeping":2,"import":1,"automotive_alarm":1,"comics":1,"photography":1,"propane":1,"vacant":4,"hydraulics":1,"costume":1,"wallpaper":1,"fabrics":1,"party_supply":1,"trophy":1,"sewing":1,"plumbing":2,"fitness_equipment":1,"model":1,"record":1,"hippy":1,"health":2,"brewing_supplies":1,"welding":1,"cash":1,"comic_books":1,"home":1,"wedding":1,"financial":1,"bridal":1,"drapery":1,"cheese":2,"auction_house":1,"appliances":1,"fasteners":1,"home_goods":1,"candles":1,"pawn":1,"donut":1,"upholstery":1,"fireplace":1,"bag":3,"photo":1,"tea":2,"boot":1,"ignition_interlock":1,"Graphic_Design":1,"wine":2,"vintage":1,"hookah":1,"herbalist":1},"leisure":{"pitch":5140,"golf_course":257,"swimming_pool":1961,"sports_centre":250,"park":2133,"playground":1245,"picnic_table":170,"fitness_centre":52,"fitness_station":21,"nature_reserve":64,"track":265,"garden":361,"slipway":103,"stadium":102,"water_park":18,"common":8,"firepit":16,"bleachers":82,"boarding, lessons":1,"marina":17,"disc_golf_course":4,"dog_park":31,"horse_riding":2,"maze":1,"racetrack":1,"festival_grounds":1,"dance":8,"sports_centre_pool":1,"shooting_range":2,"recreation_ground":45,"bowling_alley":11,"miniature_golf":11,"water park":1,"sport":3,"climbingframe":1,"swing":1,"fishing":3,"outdoor_seating":25,"bandstand":1,"plaground":1,"disc_golf":1,"sauna":1,"hackerspace":3,"yes":5,"escape_game":1,"summer_camp":1,"amusement_arcade":4,"tanning_salon":1,"ice_rink":4,"walk/run":1,"trampoline_park":1}}