{"amenity":{"place_of_worship":6285,"grave_yard":5269,"school":3157,"shelter":308,"fuel":1149,"fast_food":1516,"restaurant":2116,"post_office":352,"fire_station":293,"courthouse":78,"bench":886,"parking":7611,"bank":619,"toilets":368,"police":113,"ice_cream":56,"car_wash":120,"dentist":49,"waste_disposal":192,"services":2,"parking_space":32,"townhall":74,"hospital":173,"cafe":310,"prison":62,"community_centre":37,"kiosk":1,"fountain":182,"atm":102,"clinic":70,"library":177,"amphitheater":1,"Fire_Training_Facility":1,"bbq":17,"childcare":42,"pharmacy":215,"loading_dock":175,"animal_shelter":7,"vending_machine":43,"veterinary":45,"social_centre":6,"clock":11,"university":122,"social_facility":86,"bus_station":16,"bar":215,"bicycle_repair_station":40,"doctors":72,"bicycle_parking":285,"events_venue":8,"marketplace":23,"arts_centre":26,"stage":1,"theatre":86,"post_box":69,"public_bookcase":2,"parking_entrance":202,"cinema":52,"waste_basket":326,"recycling":27,"car_rental":26,"college":47,"swimming_pool":18,"public_building":17,"pub":80,"kindergarten":14,"sanitary_dump_station":4,"waste_transfer_station":3,"drinking_water":253,"compressed_air":5,"air_filling":1,"Amphitheater":1,"nursing_home":14,"car_pooling":3,"boat_rental":3,"charging_station":18,"weighbridge":4,"convenience":1,"yes":8,"ferry_terminal":4,"shower":3,"ranger_station":5,"casino":14,"social_club":2,"animal_boarding":8,"boat_storage":1,"studio":23,"bandstand":1,"telephone":9,"clubhouse":6,"court_house":1,"bin":2,"scrapyard":1,"taxi":1,"car_repair":1,"house":1,"driver_training":2,"car_sharing":6,"ice":1,"reception_desk":22,"food_court":12,"smoking_area":1,"public_bath":2,"planetarium":2,"gym":1,"hunting_stand":1,"gambling":2,"driving_school":3,"training":1,"audiologist":1,"device_charging_station":3,"nightclub":7,"spa":3,"seating":2,"place_of_worship;school":1,"music_school":3,"construction":2,"beauty":1,"hairdresser":1,"camera":1,"boutique":1,"bureau_de_change":2,"Family Law Attorney":1,"dojo":1,"dropbox":1,"dancing_school":1,"water_point":1,"community_center":1,"public_building;courthouse":1,"artwork":1,"confectionery":1,"hitching_post":1,"grocer":1,"bicycle_rental":71,"monastery":2,"motorcycle_parking":2,"payment_terminal":1,"music_venue":1,"waste_bags":1,"convention_centre":1,"office":1,"karaoke_box":1,"botanical_gardens":1,"brewery":1,"water_treatment_plant":1,"bell":1,"stripclub":1,"ticket_booth":3,"first_aid":2,"reception_hall":1,"exhibition_hall":1,"copyshop":1,"first aid":1,"computer":1,"w":1,"letter_box":1,"smoothies":1,"sportswear":1,"tavern":1},"shop":{"convenience":517,"deli":12,"variety_store":110,"car_repair":169,"pyrotechnics":3,"alcohol":139,"doityourself":83,"car":174,"tattoo":14,"supermarket":383,"funeral_directors":40,"radiotechnics":3,"cash":1,"hairdresser":112,"gift":55,"laundry":19,"car_parts":70,"butcher":13,"department_store":91,"garden_furniture":1,"mall":36,"beauty":105,"furniture":55,"vacant":23,"agrarian":7,"tyres":30,"computer_repair":1,"storage_rental":16,"trade":5,"gas":2,"chemist":13,"video_games":25,"mobile_phone":77,"shoes":41,"electronics":38,"general":2,"clothes":194,"hardware":47,"second_hand":24,"locksmith":2,"tobacco":15,"bicycle":41,"florist":27,"garden_centre":8,"country_store":21,"yes":93,"interior_decoration":13,"video":11,"paint":11,"farm":6,"grocery":6,"antiques":13,"Kroger":1,"sports":32,"dry_cleaning":29,"pet_grooming":4,"beverages":16,"Save A Lot":1,"auto_parts":2,"pawnbroker":20,"charity":24,"outdoor":11,"coffee":5,"bakery":43,"kiosk":7,"optician":24,"massage":7,"pet":30,"music":23,"carpet":8,"Vendor_Mall":1,"books":47,"construction":1,"bed":14,"medical_supply":3,"mobile_home":2,"jewelry":33,"wine":3,"auction":2,"fuel":1,"boutique":17,"musical_instrument":10,"copyshop":11,"craft":24,"wholesale":14,"greengrocer":20,"fabric":8,"tea":3,"bookmaker":4,"nutrition_supplements":13,"hairdresser_supply":4,"ice_cream":2,"weapons":5,"houseware":16,"stationery":28,"toys":11,"motorcycle":9,"baby_goods":4,"money_lender":5,"crafts":1,"cosmetics":11,"computer":9,"trophy":2,"fashion_accessories":2,"window_blind":2,"candles":2,"hearing_aids":3,"party":6,"hifi":3,"quilting":1,"HVAC_Equipment":1,"confectionery":11,"e-cigarette":3,"fireworks":1,"motorcycle_repair":1,"tea_room":1,"barber":3,"art":6,"tickets":11,"ticket":34,"newsagent":1,"flooring":1,"appliance":2,"groundskeeping":2,"photo":2,"cannabis":1,"interior_decoration,gift":1,"olive_oil":1,"beads":1,"shed":1,"discount":1,"bathroom_furnishing":2,"Grocery Store":1,"fur":1,"pottery":2,"vacuum_cleaner":2,"cabinets":1,"spices":2,"sewing":1,"bag":1,"water_sports":1,"military_surplus":1,"phone service":1,"tailor":2,"frame":1,"for_rent":1,"collector":1,"wedding":1,"pastry":3,"yarn":1,"upholstery":1,"scuba_diving":1,"seafood":1,"theatre":1,"computer;clothes":1,"print":1,"pasta":1,"butcher;seafood":1,"fishmonger":2,"stationary":1,"travel_agency":1,"shoe_repair":1,"signs":1,"printing":1,"erotic":2,"transit":1,"brewing_supply":1,"shoes;clothes":1,"general_store":1,"laundromat":1,"vape":1,"board":1,"fixme":2},"leisure":{"golf_course":255,"pitch":4814,"playground":1191,"park":1651,"swimming_pool":1140,"track":247,"dog_park":28,"miniature_golf":16,"fitness_centre":89,"stadium":124,"marina":82,"slipway":201,"racetrack":2,"bleachers":16,"fishing":1,"sports_centre":181,"garden":377,"horse_riding":5,"picnic_table":201,"firepit":5,"bowling_alley":12,"nature_reserve":21,"recreation_ground":9,"bandstand":2,"video_arcade":1,"water_park":14,"outdoor_seating":20,"common":32,"dance":8,"hackerspace":4,"amusement_arcade":5,"open field":1,"fitness_station":22,"ice_rink":4,"disc_golf_course":3,"adult_gaming_centre":1,"sport":1,"amphitheatre":1,"bird_hide":1,"public":1,"parking_lot":1,"massage":1,"social_club":1,"ax_throwing":1,"construction":1,"gallery":2,"stage":1,"escape_game":1,"karaoke":1,"yes":1,"private_plaza":1,"basketball court":1}}